ofxstatement_upday/__init__.py
ofxstatement_upday/download.py
ofxstatement_upday/upday.py
ofxstatement_upday-1.1.1.dist-info/METADATA
ofxstatement_upday-1.1.1.dist-info/WHEEL
ofxstatement_upday-1.1.1.dist-info/entry_points.txt
ofxstatement_upday-1.1.1.dist-info/top_level.txt
ofxstatement_upday-1.1.1.dist-info/RECORD
