Metadata-Version: 2.4
Name: ofxstatement-upday
Version: 1.1.1
Summary: Plugin per ofxstatement per importare transazioni buoni pasto UpDay
Author-email: Alfystar <alfystar1701@gmail.com>
License: GPLv3
Project-URL: Homepage, https://github.com/Alfystar/ofxstatement-upday
Project-URL: Repository, https://github.com/Alfystar/ofxstatement-upday
Project-URL: Issues, https://github.com/Alfystar/ofxstatement-upday/issues
Keywords: ofx,banking,statement,upday,buoni pasto
Classifier: Development Status :: 4 - Beta
Classifier: Programming Language :: Python :: 3
Classifier: Programming Language :: Python :: 3.9
Classifier: Programming Language :: Python :: 3.10
Classifier: Programming Language :: Python :: 3.11
Classifier: Programming Language :: Python :: 3.12
Classifier: Natural Language :: Italian
Classifier: Topic :: Office/Business :: Financial :: Accounting
Classifier: Topic :: Utilities
Classifier: Environment :: Console
Classifier: Operating System :: OS Independent
Classifier: License :: OSI Approved :: GNU General Public License v3 (GPLv3)
Requires-Python: >=3.9
Requires-Dist: ofxstatement
Requires-Dist: selenium>=4.15.0
Requires-Dist: beautifulsoup4>=4.12.0
Requires-Dist: webdriver-manager>=4.0.0
Requires-Dist: requests>=2.28.0
Provides-Extra: dev
Requires-Dist: pytest>=7.0.0; extra == "dev"
Requires-Dist: pytest-cov>=4.0.0; extra == "dev"
Requires-Dist: black>=23.0.0; extra == "dev"
Requires-Dist: flake8>=6.0.0; extra == "dev"
Provides-Extra: system-chromedriver
